{
  "RENEEB": {
    "blog_feed": "http://reneeb-perlblog.blogspot.com/feeds/posts/default",
    "blog_url": "http://reneeb-perlblog.blogspot.com",
    "github_username": "reneeb",
    "website": "http://perl-magazin.de",
    "linkedin_public_profile": "http://de.linkedin.com/in/reneebaecker",
    "perlmongers" : "Frankfurt.pm",
    "perlmongers_url" : "http://frankfurt.perlmongers.de",
    "twitter_username" : "reneeb_perl",
    "slideshare_username" : "reneebperl",
    "irc_nick" : "reneeb",
    "perlmonks_username" : "reneeb",
    "country": "Germany"
  }
}
